{
  "id": "hmda",
  "realm": "hmda",
  "notBefore": 0,
  "revokeRefreshToken": false,
  "refreshTokenMaxReuse": 0,
  "accessTokenLifespan": 300,
  "accessTokenLifespanForImplicitFlow": 900,
  "ssoSessionIdleTimeout": 1800,
  "ssoSessionMaxLifespan": 36000,
  "offlineSessionIdleTimeout": 2592000,
  "accessCodeLifespan": 60,
  "accessCodeLifespanUserAction": 3600,
  "accessCodeLifespanLogin": 1800,
  "actionTokenGeneratedByAdminLifespan": 43200,
  "actionTokenGeneratedByUserLifespan": 3600,
  "enabled": true,
  "sslRequired": "all",
  "registrationAllowed": true,
  "registrationEmailAsUsername": true,
  "rememberMe": false,
  "verifyEmail": true,
  "loginWithEmailAllowed": true,
  "duplicateEmailsAllowed": false,
  "resetPasswordAllowed": true,
  "editUsernameAllowed": false,
  "bruteForceProtected": true,
  "permanentLockout": true,
  "maxFailureWaitSeconds": 900,
  "minimumQuickLoginWaitSeconds": 60,
  "waitIncrementSeconds": 60,
  "quickLoginCheckMilliSeconds": 1000,
  "maxDeltaTimeSeconds": 43200,
  "failureFactor": 30,
  "roles": {
    "realm": [
      {
        "id": "84141257-2baa-4490-947c-ed109a9fb2e4",
        "name": "offline_access",
        "description": "${role_offline-access}",
        "scopeParamRequired": true,
        "composite": false,
        "clientRole": false,
        "containerId": "hmda"
      },
      {
        "id": "8c3bb238-8404-4460-8a88-92c80c3cfb9a",
        "name": "uma_authorization",
        "description": "${role_uma_authorization}",
        "scopeParamRequired": false,
        "composite": false,
        "clientRole": false,
        "containerId": "hmda"
      }
    ],
    "client": {
      "realm-management": [
        {
          "id": "beeec4cc-a4f5-433f-bf69-fca25cffc146",
          "name": "view-events",
          "description": "${role_view-events}",
          "scopeParamRequired": false,
          "composite": false,
          "clientRole": true,
          "containerId": "f25dac52-163f-4803-87c2-6094ecdbbf61"
        },
        {
          "id": "1dccf8b7-42af-484c-9bfd-822760c489e5",
          "name": "manage-authorization",
          "description": "${role_manage-authorization}",
          "scopeParamRequired": false,
          "composite": false,
          "clientRole": true,
          "containerId": "f25dac52-163f-4803-87c2-6094ecdbbf61"
        },
        {
          "id": "ea909e33-6590-46fb-ab47-59aec5e54b1f",
          "name": "manage-events",
          "description": "${role_manage-events}",
          "scopeParamRequired": false,
          "composite": false,
          "clientRole": true,
          "containerId": "f25dac52-163f-4803-87c2-6094ecdbbf61"
        },
        {
          "id": "3e808fd5-5599-4261-8f31-1023eb827468",
          "name": "view-authorization",
          "description": "${role_view-authorization}",
          "scopeParamRequired": false,
          "composite": false,
          "clientRole": true,
          "containerId": "f25dac52-163f-4803-87c2-6094ecdbbf61"
        },
        {
          "id": "df3d3d8b-d3a6-4bea-9f24-b40065152664",
          "name": "manage-identity-providers",
          "description": "${role_manage-identity-providers}",
          "scopeParamRequired": false,
          "composite": false,
          "clientRole": true,
          "containerId": "f25dac52-163f-4803-87c2-6094ecdbbf61"
        },
        {
          "id": "e38fc39f-22b7-44ba-98e2-a7c71b975fd9",
          "name": "view-clients",
          "description": "${role_view-clients}",
          "scopeParamRequired": false,
          "composite": true,
          "composites": {
            "client": {
              "realm-management": [
                "query-clients"
              ]
            }
          },
          "clientRole": true,
          "containerId": "f25dac52-163f-4803-87c2-6094ecdbbf61"
        },
        {
          "id": "a95c75b9-3a26-47f3-a334-f93e7335d180",
          "name": "impersonation",
          "description": "${role_impersonation}",
          "scopeParamRequired": false,
          "composite": false,
          "clientRole": true,
          "containerId": "f25dac52-163f-4803-87c2-6094ecdbbf61"
        },
        {
          "id": "257cb695-2b0c-4f1d-96e0-c73dcacc37f7",
          "name": "query-realms",
          "description": "${role_query-realms}",
          "scopeParamRequired": false,
          "composite": false,
          "clientRole": true,
          "containerId": "f25dac52-163f-4803-87c2-6094ecdbbf61"
        },
        {
          "id": "4d8833c2-e29e-489e-8b1c-f114c38c4579",
          "name": "manage-realm",
          "description": "${role_manage-realm}",
          "scopeParamRequired": false,
          "composite": false,
          "clientRole": true,
          "containerId": "f25dac52-163f-4803-87c2-6094ecdbbf61"
        },
        {
          "id": "7c53be63-d0c2-4a96-899c-a4d6a8fc046d",
          "name": "view-users",
          "description": "${role_view-users}",
          "scopeParamRequired": false,
          "composite": true,
          "composites": {
            "client": {
              "realm-management": [
                "query-groups",
                "query-users"
              ]
            }
          },
          "clientRole": true,
          "containerId": "f25dac52-163f-4803-87c2-6094ecdbbf61"
        },
        {
          "id": "b12c3bad-19c0-4c5f-98e7-8a68f190c7c7",
          "name": "realm-admin",
          "description": "${role_realm-admin}",
          "scopeParamRequired": false,
          "composite": true,
          "composites": {
            "client": {
              "realm-management": [
                "view-events",
                "manage-authorization",
                "manage-events",
                "view-authorization",
                "manage-identity-providers",
                "view-clients",
                "impersonation",
                "query-realms",
                "manage-realm",
                "view-users",
                "view-realm",
                "view-identity-providers",
                "query-groups",
                "create-client",
                "manage-clients",
                "query-users",
                "query-clients",
                "manage-users"
              ]
            }
          },
          "clientRole": true,
          "containerId": "f25dac52-163f-4803-87c2-6094ecdbbf61"
        },
        {
          "id": "475e94ac-b43d-44e6-b29f-c1c0b2749ad9",
          "name": "view-realm",
          "description": "${role_view-realm}",
          "scopeParamRequired": false,
          "composite": false,
          "clientRole": true,
          "containerId": "f25dac52-163f-4803-87c2-6094ecdbbf61"
        },
        {
          "id": "de220a09-b4bb-492f-aea5-6d735b099b02",
          "name": "view-identity-providers",
          "description": "${role_view-identity-providers}",
          "scopeParamRequired": false,
          "composite": false,
          "clientRole": true,
          "containerId": "f25dac52-163f-4803-87c2-6094ecdbbf61"
        },
        {
          "id": "5519f81b-b8c7-4034-8d6d-7e7ca7c3dfe6",
          "name": "query-groups",
          "description": "${role_query-groups}",
          "scopeParamRequired": false,
          "composite": false,
          "clientRole": true,
          "containerId": "f25dac52-163f-4803-87c2-6094ecdbbf61"
        },
        {
          "id": "c99ac0ce-9187-4de8-9a80-d89f20ff415c",
          "name": "create-client",
          "description": "${role_create-client}",
          "scopeParamRequired": false,
          "composite": false,
          "clientRole": true,
          "containerId": "f25dac52-163f-4803-87c2-6094ecdbbf61"
        },
        {
          "id": "a4c371e6-e475-464a-82df-ee4ebfcc67bd",
          "name": "manage-clients",
          "description": "${role_manage-clients}",
          "scopeParamRequired": false,
          "composite": false,
          "clientRole": true,
          "containerId": "f25dac52-163f-4803-87c2-6094ecdbbf61"
        },
        {
          "id": "1167a18e-34d8-4b05-a9a3-548a776ac028",
          "name": "query-users",
          "description": "${role_query-users}",
          "scopeParamRequired": false,
          "composite": false,
          "clientRole": true,
          "containerId": "f25dac52-163f-4803-87c2-6094ecdbbf61"
        },
        {
          "id": "445b9c49-aaec-4a7b-8a63-9d208e81b6c0",
          "name": "query-clients",
          "description": "${role_query-clients}",
          "scopeParamRequired": false,
          "composite": false,
          "clientRole": true,
          "containerId": "f25dac52-163f-4803-87c2-6094ecdbbf61"
        },
        {
          "id": "65fda1b7-ba03-4d13-8342-181faf463584",
          "name": "manage-users",
          "description": "${role_manage-users}",
          "scopeParamRequired": false,
          "composite": false,
          "clientRole": true,
          "containerId": "f25dac52-163f-4803-87c2-6094ecdbbf61"
        }
      ],
      "security-admin-console": [],
      "admin-cli": [],
      "broker": [
        {
          "id": "647b4843-3da0-4802-a683-9ee67d14a0e3",
          "name": "read-token",
          "description": "${role_read-token}",
          "scopeParamRequired": false,
          "composite": false,
          "clientRole": true,
          "containerId": "da02716f-8e9d-4613-86d6-3e5b218e91c5"
        }
      ],
      "hmda-api": [],
      "account": [
        {
          "id": "0b0493cc-ddac-4eb6-af95-97ce6ea14dcb",
          "name": "view-profile",
          "description": "${role_view-profile}",
          "scopeParamRequired": false,
          "composite": false,
          "clientRole": true,
          "containerId": "1b0cb335-03b1-4df7-9913-2939631a818b"
        },
        {
          "id": "88478c8c-5c13-44dc-9dd6-7f2716c4a746",
          "name": "manage-account-links",
          "description": "${role_manage-account-links}",
          "scopeParamRequired": false,
          "composite": false,
          "clientRole": true,
          "containerId": "1b0cb335-03b1-4df7-9913-2939631a818b"
        },
        {
          "id": "37efa70e-b58c-4ceb-b3b6-a99f876a3955",
          "name": "manage-account",
          "description": "${role_manage-account}",
          "scopeParamRequired": false,
          "composite": true,
          "composites": {
            "client": {
              "account": [
                "manage-account-links"
              ]
            }
          },
          "clientRole": true,
          "containerId": "1b0cb335-03b1-4df7-9913-2939631a818b"
        }
      ]
    }
  },
  "groups": [],
  "defaultRoles": [
    "offline_access",
    "uma_authorization"
  ],
  "requiredCredentials": [
    "password"
  ],
  "passwordPolicy": "forceExpiredPasswordChange(90) and length(12) and passwordHistory(10) and upperCase(1) and lowerCase(1) and digits(1) and specialChars(1) and notUsername(undefined) and hashIterations(27500)",
  "otpPolicyType": "totp",
  "otpPolicyAlgorithm": "HmacSHA1",
  "otpPolicyInitialCounter": 0,
  "otpPolicyDigits": 6,
  "otpPolicyLookAheadWindow": 1,
  "otpPolicyPeriod": 30,
  "clients": [
    {
      "id": "c5266bc3-fa63-4801-b5d1-80987ba56c2a",
      "clientId": "security-admin-console",
      "name": "${client_security-admin-console}",
      "baseUrl": "/auth/admin/hmda/console/index.html",
      "surrogateAuthRequired": false,
      "enabled": true,
      "clientAuthenticatorType": "client-secret",
      "secret": "**********",
      "redirectUris": [
        "/auth/admin/hmda/console/*"
      ],
      "webOrigins": [],
      "notBefore": 0,
      "bearerOnly": false,
      "consentRequired": false,
      "standardFlowEnabled": true,
      "implicitFlowEnabled": false,
      "directAccessGrantsEnabled": false,
      "serviceAccountsEnabled": false,
      "publicClient": true,
      "frontchannelLogout": false,
      "protocol": "openid-connect",
      "attributes": {},
      "fullScopeAllowed": false,
      "nodeReRegistrationTimeout": 0,
      "protocolMappers": [
        {
          "id": "8f51a479-c2d1-4016-9387-a8a159112f17",
          "name": "email",
          "protocol": "openid-connect",
          "protocolMapper": "oidc-usermodel-property-mapper",
          "consentRequired": true,
          "consentText": "${email}",
          "config": {
            "userinfo.token.claim": "true",
            "user.attribute": "email",
            "id.token.claim": "true",
            "access.token.claim": "true",
            "claim.name": "email",
            "jsonType.label": "String"
          }
        },
        {
          "id": "508fec69-450a-4ae2-bd3f-f90ca0d99bfc",
          "name": "full name",
          "protocol": "openid-connect",
          "protocolMapper": "oidc-full-name-mapper",
          "consentRequired": true,
          "consentText": "${fullName}",
          "config": {
            "id.token.claim": "true",
            "access.token.claim": "true"
          }
        },
        {
          "id": "1665ca7e-c198-4d5c-9801-ef85ae8c7c31",
          "name": "role list",
          "protocol": "saml",
          "protocolMapper": "saml-role-list-mapper",
          "consentRequired": false,
          "config": {
            "single": "false",
            "attribute.nameformat": "Basic",
            "attribute.name": "Role"
          }
        },
        {
          "id": "9d4a78fc-c0dd-44a8-9a2d-87688bd4a816",
          "name": "given name",
          "protocol": "openid-connect",
          "protocolMapper": "oidc-usermodel-property-mapper",
          "consentRequired": true,
          "consentText": "${givenName}",
          "config": {
            "userinfo.token.claim": "true",
            "user.attribute": "firstName",
            "id.token.claim": "true",
            "access.token.claim": "true",
            "claim.name": "given_name",
            "jsonType.label": "String"
          }
        },
        {
          "id": "fe391418-16b1-4dad-a266-37a7e4931376",
          "name": "locale",
          "protocol": "openid-connect",
          "protocolMapper": "oidc-usermodel-attribute-mapper",
          "consentRequired": false,
          "consentText": "${locale}",
          "config": {
            "userinfo.token.claim": "true",
            "user.attribute": "locale",
            "id.token.claim": "true",
            "access.token.claim": "true",
            "claim.name": "locale",
            "jsonType.label": "String"
          }
        },
        {
          "id": "844105da-5a92-4841-8e40-f1824d8d4c1f",
          "name": "family name",
          "protocol": "openid-connect",
          "protocolMapper": "oidc-usermodel-property-mapper",
          "consentRequired": true,
          "consentText": "${familyName}",
          "config": {
            "userinfo.token.claim": "true",
            "user.attribute": "lastName",
            "id.token.claim": "true",
            "access.token.claim": "true",
            "claim.name": "family_name",
            "jsonType.label": "String"
          }
        },
        {
          "id": "e7d1a9d2-b6c7-4728-910e-938fc9ffe9f5",
          "name": "username",
          "protocol": "openid-connect",
          "protocolMapper": "oidc-usermodel-property-mapper",
          "consentRequired": true,
          "consentText": "${username}",
          "config": {
            "userinfo.token.claim": "true",
            "user.attribute": "username",
            "id.token.claim": "true",
            "access.token.claim": "true",
            "claim.name": "preferred_username",
            "jsonType.label": "String"
          }
        }
      ],
      "useTemplateConfig": false,
      "useTemplateScope": false,
      "useTemplateMappers": false
    },
    {
      "id": "f25dac52-163f-4803-87c2-6094ecdbbf61",
      "clientId": "realm-management",
      "name": "${client_realm-management}",
      "surrogateAuthRequired": false,
      "enabled": true,
      "clientAuthenticatorType": "client-secret",
      "secret": "**********",
      "redirectUris": [],
      "webOrigins": [],
      "notBefore": 0,
      "bearerOnly": true,
      "consentRequired": false,
      "standardFlowEnabled": true,
      "implicitFlowEnabled": false,
      "directAccessGrantsEnabled": false,
      "serviceAccountsEnabled": false,
      "publicClient": false,
      "frontchannelLogout": false,
      "protocol": "openid-connect",
      "attributes": {},
      "fullScopeAllowed": false,
      "nodeReRegistrationTimeout": 0,
      "protocolMappers": [
        {
          "id": "dc67c869-255f-480a-87aa-b927af6c3f3b",
          "name": "email",
          "protocol": "openid-connect",
          "protocolMapper": "oidc-usermodel-property-mapper",
          "consentRequired": true,
          "consentText": "${email}",
          "config": {
            "userinfo.token.claim": "true",
            "user.attribute": "email",
            "id.token.claim": "true",
            "access.token.claim": "true",
            "claim.name": "email",
            "jsonType.label": "String"
          }
        },
        {
          "id": "6eae3476-3630-4f10-b470-06f4205764e5",
          "name": "given name",
          "protocol": "openid-connect",
          "protocolMapper": "oidc-usermodel-property-mapper",
          "consentRequired": true,
          "consentText": "${givenName}",
          "config": {
            "userinfo.token.claim": "true",
            "user.attribute": "firstName",
            "id.token.claim": "true",
            "access.token.claim": "true",
            "claim.name": "given_name",
            "jsonType.label": "String"
          }
        },
        {
          "id": "8e9824dc-44fe-405b-8f44-c08061bac295",
          "name": "role list",
          "protocol": "saml",
          "protocolMapper": "saml-role-list-mapper",
          "consentRequired": false,
          "config": {
            "single": "false",
            "attribute.nameformat": "Basic",
            "attribute.name": "Role"
          }
        },
        {
          "id": "43e160bc-bf3b-4028-abfc-45392edbd5b2",
          "name": "username",
          "protocol": "openid-connect",
          "protocolMapper": "oidc-usermodel-property-mapper",
          "consentRequired": true,
          "consentText": "${username}",
          "config": {
            "userinfo.token.claim": "true",
            "user.attribute": "username",
            "id.token.claim": "true",
            "access.token.claim": "true",
            "claim.name": "preferred_username",
            "jsonType.label": "String"
          }
        },
        {
          "id": "cc46317a-33b6-4189-84a5-5224f37e2826",
          "name": "family name",
          "protocol": "openid-connect",
          "protocolMapper": "oidc-usermodel-property-mapper",
          "consentRequired": true,
          "consentText": "${familyName}",
          "config": {
            "userinfo.token.claim": "true",
            "user.attribute": "lastName",
            "id.token.claim": "true",
            "access.token.claim": "true",
            "claim.name": "family_name",
            "jsonType.label": "String"
          }
        },
        {
          "id": "f0624239-4b78-4a1d-adfc-96f6ffb9e97c",
          "name": "full name",
          "protocol": "openid-connect",
          "protocolMapper": "oidc-full-name-mapper",
          "consentRequired": true,
          "consentText": "${fullName}",
          "config": {
            "id.token.claim": "true",
            "access.token.claim": "true"
          }
        }
      ],
      "useTemplateConfig": false,
      "useTemplateScope": false,
      "useTemplateMappers": false
    },
    {
      "id": "da02716f-8e9d-4613-86d6-3e5b218e91c5",
      "clientId": "broker",
      "name": "${client_broker}",
      "surrogateAuthRequired": false,
      "enabled": true,
      "clientAuthenticatorType": "client-secret",
      "secret": "**********",
      "redirectUris": [],
      "webOrigins": [],
      "notBefore": 0,
      "bearerOnly": false,
      "consentRequired": false,
      "standardFlowEnabled": true,
      "implicitFlowEnabled": false,
      "directAccessGrantsEnabled": false,
      "serviceAccountsEnabled": false,
      "publicClient": false,
      "frontchannelLogout": false,
      "protocol": "openid-connect",
      "attributes": {},
      "fullScopeAllowed": false,
      "nodeReRegistrationTimeout": 0,
      "protocolMappers": [
        {
          "id": "4a155298-7387-4ea0-a3d7-4a81bf6d212f",
          "name": "email",
          "protocol": "openid-connect",
          "protocolMapper": "oidc-usermodel-property-mapper",
          "consentRequired": true,
          "consentText": "${email}",
          "config": {
            "userinfo.token.claim": "true",
            "user.attribute": "email",
            "id.token.claim": "true",
            "access.token.claim": "true",
            "claim.name": "email",
            "jsonType.label": "String"
          }
        },
        {
          "id": "b88aab2e-56a8-40ce-a7da-c6306da6b9de",
          "name": "role list",
          "protocol": "saml",
          "protocolMapper": "saml-role-list-mapper",
          "consentRequired": false,
          "config": {
            "single": "false",
            "attribute.nameformat": "Basic",
            "attribute.name": "Role"
          }
        },
        {
          "id": "5d87042b-0c96-4847-970b-aab6e22b19f4",
          "name": "username",
          "protocol": "openid-connect",
          "protocolMapper": "oidc-usermodel-property-mapper",
          "consentRequired": true,
          "consentText": "${username}",
          "config": {
            "userinfo.token.claim": "true",
            "user.attribute": "username",
            "id.token.claim": "true",
            "access.token.claim": "true",
            "claim.name": "preferred_username",
            "jsonType.label": "String"
          }
        },
        {
          "id": "851638d8-5a5c-441d-b2c5-b4fcbe66bad8",
          "name": "family name",
          "protocol": "openid-connect",
          "protocolMapper": "oidc-usermodel-property-mapper",
          "consentRequired": true,
          "consentText": "${familyName}",
          "config": {
            "userinfo.token.claim": "true",
            "user.attribute": "lastName",
            "id.token.claim": "true",
            "access.token.claim": "true",
            "claim.name": "family_name",
            "jsonType.label": "String"
          }
        },
        {
          "id": "2d072951-c0c6-4a6e-a724-e09e9d5b8579",
          "name": "given name",
          "protocol": "openid-connect",
          "protocolMapper": "oidc-usermodel-property-mapper",
          "consentRequired": true,
          "consentText": "${givenName}",
          "config": {
            "userinfo.token.claim": "true",
            "user.attribute": "firstName",
            "id.token.claim": "true",
            "access.token.claim": "true",
            "claim.name": "given_name",
            "jsonType.label": "String"
          }
        },
        {
          "id": "f3550010-e5b1-4612-888a-6618d6ffddd1",
          "name": "full name",
          "protocol": "openid-connect",
          "protocolMapper": "oidc-full-name-mapper",
          "consentRequired": true,
          "consentText": "${fullName}",
          "config": {
            "id.token.claim": "true",
            "access.token.claim": "true"
          }
        }
      ],
      "useTemplateConfig": false,
      "useTemplateScope": false,
      "useTemplateMappers": false
    },
    {
      "id": "1b0cb335-03b1-4df7-9913-2939631a818b",
      "clientId": "account",
      "name": "${client_account}",
      "baseUrl": "/auth/realms/hmda/account",
      "surrogateAuthRequired": false,
      "enabled": true,
      "clientAuthenticatorType": "client-secret",
      "secret": "**********",
      "defaultRoles": [
        "view-profile",
        "manage-account"
      ],
      "redirectUris": [
        "/auth/realms/hmda/account/*"
      ],
      "webOrigins": [],
      "notBefore": 0,
      "bearerOnly": false,
      "consentRequired": false,
      "standardFlowEnabled": true,
      "implicitFlowEnabled": false,
      "directAccessGrantsEnabled": false,
      "serviceAccountsEnabled": false,
      "publicClient": false,
      "frontchannelLogout": false,
      "protocol": "openid-connect",
      "attributes": {},
      "fullScopeAllowed": false,
      "nodeReRegistrationTimeout": 0,
      "protocolMappers": [
        {
          "id": "03212054-252c-4da9-984f-9809ed72db0a",
          "name": "username",
          "protocol": "openid-connect",
          "protocolMapper": "oidc-usermodel-property-mapper",
          "consentRequired": true,
          "consentText": "${username}",
          "config": {
            "userinfo.token.claim": "true",
            "user.attribute": "username",
            "id.token.claim": "true",
            "access.token.claim": "true",
            "claim.name": "preferred_username",
            "jsonType.label": "String"
          }
        },
        {
          "id": "7c8ffca9-97c4-4333-84c2-3b87900a612a",
          "name": "family name",
          "protocol": "openid-connect",
          "protocolMapper": "oidc-usermodel-property-mapper",
          "consentRequired": true,
          "consentText": "${familyName}",
          "config": {
            "userinfo.token.claim": "true",
            "user.attribute": "lastName",
            "id.token.claim": "true",
            "access.token.claim": "true",
            "claim.name": "family_name",
            "jsonType.label": "String"
          }
        },
        {
          "id": "00e0868a-44a3-4501-933a-c9939aaafe75",
          "name": "given name",
          "protocol": "openid-connect",
          "protocolMapper": "oidc-usermodel-property-mapper",
          "consentRequired": true,
          "consentText": "${givenName}",
          "config": {
            "userinfo.token.claim": "true",
            "user.attribute": "firstName",
            "id.token.claim": "true",
            "access.token.claim": "true",
            "claim.name": "given_name",
            "jsonType.label": "String"
          }
        },
        {
          "id": "371ea4ce-216f-41f4-8143-a5c0438dc061",
          "name": "full name",
          "protocol": "openid-connect",
          "protocolMapper": "oidc-full-name-mapper",
          "consentRequired": true,
          "consentText": "${fullName}",
          "config": {
            "id.token.claim": "true",
            "access.token.claim": "true"
          }
        },
        {
          "id": "94e3b3e2-ffad-433d-ad9b-699215b62c3d",
          "name": "role list",
          "protocol": "saml",
          "protocolMapper": "saml-role-list-mapper",
          "consentRequired": false,
          "config": {
            "single": "false",
            "attribute.nameformat": "Basic",
            "attribute.name": "Role"
          }
        },
        {
          "id": "061898da-f5e5-4c52-8939-7aa673adb9af",
          "name": "email",
          "protocol": "openid-connect",
          "protocolMapper": "oidc-usermodel-property-mapper",
          "consentRequired": true,
          "consentText": "${email}",
          "config": {
            "userinfo.token.claim": "true",
            "user.attribute": "email",
            "id.token.claim": "true",
            "access.token.claim": "true",
            "claim.name": "email",
            "jsonType.label": "String"
          }
        }
      ],
      "useTemplateConfig": false,
      "useTemplateScope": false,
      "useTemplateMappers": false
    },
    {
      "id": "1a6be6ca-855e-47b2-91cd-407f3c1e776e",
      "clientId": "hmda-api",
      "surrogateAuthRequired": false,
      "enabled": true,
      "clientAuthenticatorType": "client-secret",
      "secret": "**********",
      "redirectUris": "{{REDIRECT_URIS}}",
      "webOrigins": [
        "*"
      ],
      "notBefore": 0,
      "bearerOnly": false,
      "consentRequired": false,
      "standardFlowEnabled": false,
      "implicitFlowEnabled": true,
      "directAccessGrantsEnabled": false,
      "serviceAccountsEnabled": false,
      "publicClient": true,
      "frontchannelLogout": false,
      "protocol": "openid-connect",
      "attributes": {
        "saml.assertion.signature": "false",
        "saml.force.post.binding": "false",
        "saml.multivalued.roles": "false",
        "saml.encrypt": "false",
        "saml_force_name_id_format": "false",
        "saml.client.signature": "false",
        "saml.authnstatement": "false",
        "saml.server.signature": "false",
        "saml.server.signature.keyinfo.ext": "false",
        "saml.onetimeuse.condition": "false"
      },
      "fullScopeAllowed": true,
      "nodeReRegistrationTimeout": -1,
      "protocolMappers": [
        {
          "id": "13228c77-8e2b-436a-be1e-ce13ffa66fe7",
          "name": "family name",
          "protocol": "openid-connect",
          "protocolMapper": "oidc-usermodel-property-mapper",
          "consentRequired": true,
          "consentText": "${familyName}",
          "config": {
            "userinfo.token.claim": "true",
            "user.attribute": "lastName",
            "id.token.claim": "true",
            "access.token.claim": "true",
            "claim.name": "family_name",
            "jsonType.label": "String"
          }
        },
        {
          "id": "7c49f6bf-6a02-4436-9b5a-20cadab13659",
          "name": "Institutions",
          "protocol": "openid-connect",
          "protocolMapper": "oidc-usermodel-attribute-mapper",
          "consentRequired": false,
          "config": {
            "userinfo.token.claim": "true",
            "multivalued": "",
            "user.attribute": "institutions",
            "id.token.claim": "true",
            "access.token.claim": "true",
            "claim.name": "institutions",
            "jsonType.label": "String"
          }
        },
        {
          "id": "270c0952-109d-4f6d-862f-ff043f78e805",
          "name": "email",
          "protocol": "openid-connect",
          "protocolMapper": "oidc-usermodel-property-mapper",
          "consentRequired": true,
          "consentText": "${email}",
          "config": {
            "userinfo.token.claim": "true",
            "user.attribute": "email",
            "id.token.claim": "true",
            "access.token.claim": "true",
            "claim.name": "email",
            "jsonType.label": "String"
          }
        },
        {
          "id": "acafed75-6235-4276-87c0-2b7793ef04e0",
          "name": "username",
          "protocol": "openid-connect",
          "protocolMapper": "oidc-usermodel-property-mapper",
          "consentRequired": true,
          "consentText": "${username}",
          "config": {
            "userinfo.token.claim": "true",
            "user.attribute": "username",
            "id.token.claim": "true",
            "access.token.claim": "true",
            "claim.name": "preferred_username",
            "jsonType.label": "String"
          }
        },
        {
          "id": "ed96eedf-17a2-4a35-9ba5-ce852e876d3f",
          "name": "given name",
          "protocol": "openid-connect",
          "protocolMapper": "oidc-usermodel-property-mapper",
          "consentRequired": true,
          "consentText": "${givenName}",
          "config": {
            "userinfo.token.claim": "true",
            "user.attribute": "firstName",
            "id.token.claim": "true",
            "access.token.claim": "true",
            "claim.name": "given_name",
            "jsonType.label": "String"
          }
        },
        {
          "id": "a634e093-641f-47b7-b615-8aeb07c803f3",
          "name": "role list",
          "protocol": "saml",
          "protocolMapper": "saml-role-list-mapper",
          "consentRequired": false,
          "config": {
            "single": "false",
            "attribute.nameformat": "Basic",
            "attribute.name": "Role"
          }
        },
        {
          "id": "4557b503-2b12-4b6b-9366-1e1ccec6da39",
          "name": "full name",
          "protocol": "openid-connect",
          "protocolMapper": "oidc-full-name-mapper",
          "consentRequired": true,
          "consentText": "${fullName}",
          "config": {
            "id.token.claim": "true",
            "access.token.claim": "true"
          }
        }
      ],
      "useTemplateConfig": false,
      "useTemplateScope": false,
      "useTemplateMappers": false
    },
    {
      "id": "890abec9-3e48-4f45-96bc-0f550ded0f8c",
      "clientId": "admin-cli",
      "name": "${client_admin-cli}",
      "surrogateAuthRequired": false,
      "enabled": true,
      "clientAuthenticatorType": "client-secret",
      "secret": "**********",
      "redirectUris": [],
      "webOrigins": [],
      "notBefore": 0,
      "bearerOnly": false,
      "consentRequired": false,
      "standardFlowEnabled": false,
      "implicitFlowEnabled": false,
      "directAccessGrantsEnabled": true,
      "serviceAccountsEnabled": false,
      "publicClient": true,
      "frontchannelLogout": false,
      "protocol": "openid-connect",
      "attributes": {},
      "fullScopeAllowed": false,
      "nodeReRegistrationTimeout": 0,
      "protocolMappers": [
        {
          "id": "269b7074-918b-4e11-9ccf-8f4116f9ed37",
          "name": "username",
          "protocol": "openid-connect",
          "protocolMapper": "oidc-usermodel-property-mapper",
          "consentRequired": true,
          "consentText": "${username}",
          "config": {
            "userinfo.token.claim": "true",
            "user.attribute": "username",
            "id.token.claim": "true",
            "access.token.claim": "true",
            "claim.name": "preferred_username",
            "jsonType.label": "String"
          }
        },
        {
          "id": "f386ce5d-1637-44f7-8746-1c082f647b3f",
          "name": "email",
          "protocol": "openid-connect",
          "protocolMapper": "oidc-usermodel-property-mapper",
          "consentRequired": true,
          "consentText": "${email}",
          "config": {
            "userinfo.token.claim": "true",
            "user.attribute": "email",
            "id.token.claim": "true",
            "access.token.claim": "true",
            "claim.name": "email",
            "jsonType.label": "String"
          }
        },
        {
          "id": "e81a4d7c-f5b0-4630-8ddf-4d1ffca08897",
          "name": "family name",
          "protocol": "openid-connect",
          "protocolMapper": "oidc-usermodel-property-mapper",
          "consentRequired": true,
          "consentText": "${familyName}",
          "config": {
            "userinfo.token.claim": "true",
            "user.attribute": "lastName",
            "id.token.claim": "true",
            "access.token.claim": "true",
            "claim.name": "family_name",
            "jsonType.label": "String"
          }
        },
        {
          "id": "496e33fd-165b-49b1-873b-7dfca34bc823",
          "name": "role list",
          "protocol": "saml",
          "protocolMapper": "saml-role-list-mapper",
          "consentRequired": false,
          "config": {
            "single": "false",
            "attribute.nameformat": "Basic",
            "attribute.name": "Role"
          }
        },
        {
          "id": "ab8a97b6-5709-4e37-85cf-5d8355168251",
          "name": "given name",
          "protocol": "openid-connect",
          "protocolMapper": "oidc-usermodel-property-mapper",
          "consentRequired": true,
          "consentText": "${givenName}",
          "config": {
            "userinfo.token.claim": "true",
            "user.attribute": "firstName",
            "id.token.claim": "true",
            "access.token.claim": "true",
            "claim.name": "given_name",
            "jsonType.label": "String"
          }
        },
        {
          "id": "2f26ef22-f121-4e9b-9eec-6f2d0c97a885",
          "name": "full name",
          "protocol": "openid-connect",
          "protocolMapper": "oidc-full-name-mapper",
          "consentRequired": true,
          "consentText": "${fullName}",
          "config": {
            "id.token.claim": "true",
            "access.token.claim": "true"
          }
        }
      ],
      "useTemplateConfig": false,
      "useTemplateScope": false,
      "useTemplateMappers": false
    }
  ],
  "clientTemplates": [],
  "browserSecurityHeaders": {
    "xContentTypeOptions": "nosniff",
    "xRobotsTag": "none",
    "xFrameOptions": "SAMEORIGIN",
    "xXSSProtection": "1; mode=block",
    "contentSecurityPolicy": "frame-src 'self'; frame-ancestors 'self'; object-src 'none';"
  },
  "smtpServer": {
    "host": "{{SMTP_SERVER}}",
    "port": "{{SMTP_PORT}}",
    "from": "noreply@cfpb.gov",
    "starttls": "",
    "auth": "",
    "ssl": ""
  },
  "loginTheme": "hmda",
  "emailTheme": "hmda",
  "eventsEnabled": false,
  "eventsListeners": [
    "jboss-logging"
  ],
  "enabledEventTypes": [],
  "adminEventsEnabled": false,
  "adminEventsDetailsEnabled": false,
  "components": {
    "org.keycloak.services.clientregistration.policy.ClientRegistrationPolicy": [
      {
        "id": "93378578-992e-44f6-b23c-e5f2f33d4285",
        "name": "Allowed Protocol Mapper Types",
        "providerId": "allowed-protocol-mappers",
        "subType": "authenticated",
        "subComponents": {},
        "config": {
          "allowed-protocol-mapper-types": [
            "saml-user-property-mapper",
            "oidc-address-mapper",
            "oidc-sha256-pairwise-sub-mapper",
            "oidc-usermodel-attribute-mapper",
            "oidc-full-name-mapper",
            "saml-role-list-mapper",
            "oidc-usermodel-property-mapper",
            "saml-user-attribute-mapper"
          ],
          "consent-required-for-all-mappers": [
            "true"
          ]
        }
      },
      {
        "id": "db005e58-ffbc-4b99-a94c-6a2a46befb94",
        "name": "Allowed Client Templates",
        "providerId": "allowed-client-templates",
        "subType": "authenticated",
        "subComponents": {},
        "config": {}
      },
      {
        "id": "dccebb9e-2410-4837-9106-9327ca39c671",
        "name": "Allowed Client Templates",
        "providerId": "allowed-client-templates",
        "subType": "anonymous",
        "subComponents": {},
        "config": {}
      },
      {
        "id": "9b464ab0-a872-40c1-9c67-d06d4dd4dc78",
        "name": "Allowed Protocol Mapper Types",
        "providerId": "allowed-protocol-mappers",
        "subType": "anonymous",
        "subComponents": {},
        "config": {
          "allowed-protocol-mapper-types": [
            "saml-user-property-mapper",
            "oidc-usermodel-property-mapper",
            "oidc-usermodel-attribute-mapper",
            "oidc-sha256-pairwise-sub-mapper",
            "oidc-address-mapper",
            "saml-user-attribute-mapper",
            "oidc-full-name-mapper",
            "saml-role-list-mapper"
          ],
          "consent-required-for-all-mappers": [
            "true"
          ]
        }
      },
      {
        "id": "41ac4029-375b-40aa-bcc5-91b37af8d811",
        "name": "Trusted Hosts",
        "providerId": "trusted-hosts",
        "subType": "anonymous",
        "subComponents": {},
        "config": {
          "host-sending-registration-request-must-match": [
            "true"
          ],
          "client-uris-must-match": [
            "true"
          ]
        }
      },
      {
        "id": "aae23ad9-caf5-47a9-8ca6-f5db23f05448",
        "name": "Max Clients Limit",
        "providerId": "max-clients",
        "subType": "anonymous",
        "subComponents": {},
        "config": {
          "max-clients": [
            "200"
          ]
        }
      },
      {
        "id": "96a26148-e461-485e-b8d3-94a3f1c15c7b",
        "name": "Consent Required",
        "providerId": "consent-required",
        "subType": "anonymous",
        "subComponents": {},
        "config": {}
      },
      {
        "id": "29ba7ba2-2f03-40ab-90cf-675f92548284",
        "name": "Full Scope Disabled",
        "providerId": "scope",
        "subType": "anonymous",
        "subComponents": {},
        "config": {}
      }
    ],
    "org.keycloak.keys.KeyProvider": [
      {
        "id": "71d8461b-9e4f-4e09-9df5-d4015a26b7cd",
        "name": "hmac-generated",
        "providerId": "hmac-generated",
        "subComponents": {},
        "config": {
          "priority": [
            "100"
          ]
        }
      },
      {
        "id": "b7c5a6ae-188c-4120-93cd-5f9057e7d11e",
        "name": "aes-generated",
        "providerId": "aes-generated",
        "subComponents": {},
        "config": {
          "priority": [
            "100"
          ]
        }
      },
      {
        "id": "3c6a9302-026b-428c-af4e-bc4aa753082a",
        "name": "rsa-generated",
        "providerId": "rsa-generated",
        "subComponents": {},
        "config": {
          "priority": [
            "100"
          ]
        }
      }
    ]
  },
  "internationalizationEnabled": false,
  "supportedLocales": [
    ""
  ],
  "authenticationFlows": [
    {
      "id": "060c955d-8804-4afc-ba2b-c497ff6b370d",
      "alias": "Handle Existing Account",
      "description": "Handle what to do if there is existing account with same email/username like authenticated identity provider",
      "providerId": "basic-flow",
      "topLevel": false,
      "builtIn": true,
      "authenticationExecutions": [
        {
          "authenticator": "idp-confirm-link",
          "requirement": "REQUIRED",
          "priority": 10,
          "userSetupAllowed": false,
          "autheticatorFlow": false
        },
        {
          "authenticator": "idp-email-verification",
          "requirement": "ALTERNATIVE",
          "priority": 20,
          "userSetupAllowed": false,
          "autheticatorFlow": false
        },
        {
          "requirement": "ALTERNATIVE",
          "priority": 30,
          "flowAlias": "Verify Existing Account by Re-authentication",
          "userSetupAllowed": false,
          "autheticatorFlow": true
        }
      ]
    },
    {
      "id": "f9ee1d5f-d863-4d69-9457-bba5b966e960",
      "alias": "Verify Existing Account by Re-authentication",
      "description": "Reauthentication of existing account",
      "providerId": "basic-flow",
      "topLevel": false,
      "builtIn": true,
      "authenticationExecutions": [
        {
          "authenticator": "idp-username-password-form",
          "requirement": "REQUIRED",
          "priority": 10,
          "userSetupAllowed": false,
          "autheticatorFlow": false
        },
        {
          "authenticator": "auth-otp-form",
          "requirement": "OPTIONAL",
          "priority": 20,
          "userSetupAllowed": false,
          "autheticatorFlow": false
        }
      ]
    },
    {
      "id": "689640e4-bc79-4af3-aad3-a3a3423e3d36",
      "alias": "browser",
      "description": "browser based authentication",
      "providerId": "basic-flow",
      "topLevel": true,
      "builtIn": true,
      "authenticationExecutions": [
        {
          "authenticator": "auth-cookie",
          "requirement": "ALTERNATIVE",
          "priority": 10,
          "userSetupAllowed": false,
          "autheticatorFlow": false
        },
        {
          "authenticator": "auth-spnego",
          "requirement": "DISABLED",
          "priority": 20,
          "userSetupAllowed": false,
          "autheticatorFlow": false
        },
        {
          "authenticator": "identity-provider-redirector",
          "requirement": "ALTERNATIVE",
          "priority": 25,
          "userSetupAllowed": false,
          "autheticatorFlow": false
        },
        {
          "requirement": "ALTERNATIVE",
          "priority": 30,
          "flowAlias": "forms",
          "userSetupAllowed": false,
          "autheticatorFlow": true
        }
      ]
    },
    {
      "id": "e18e4495-ea3c-41c4-9a8b-cd4043272c0c",
      "alias": "clients",
      "description": "Base authentication for clients",
      "providerId": "client-flow",
      "topLevel": true,
      "builtIn": true,
      "authenticationExecutions": [
        {
          "authenticator": "client-secret",
          "requirement": "ALTERNATIVE",
          "priority": 10,
          "userSetupAllowed": false,
          "autheticatorFlow": false
        },
        {
          "authenticator": "client-jwt",
          "requirement": "ALTERNATIVE",
          "priority": 20,
          "userSetupAllowed": false,
          "autheticatorFlow": false
        }
      ]
    },
    {
      "id": "688daac4-9652-4c7c-814f-651a0d8298e8",
      "alias": "direct grant",
      "description": "OpenID Connect Resource Owner Grant",
      "providerId": "basic-flow",
      "topLevel": true,
      "builtIn": true,
      "authenticationExecutions": [
        {
          "authenticator": "direct-grant-validate-username",
          "requirement": "REQUIRED",
          "priority": 10,
          "userSetupAllowed": false,
          "autheticatorFlow": false
        },
        {
          "authenticator": "direct-grant-validate-password",
          "requirement": "REQUIRED",
          "priority": 20,
          "userSetupAllowed": false,
          "autheticatorFlow": false
        },
        {
          "authenticator": "direct-grant-validate-otp",
          "requirement": "OPTIONAL",
          "priority": 30,
          "userSetupAllowed": false,
          "autheticatorFlow": false
        }
      ]
    },
    {
      "id": "d196c1ff-0798-459e-bb8d-e58d1145fbd2",
      "alias": "docker auth",
      "description": "Used by Docker clients to authenticate against the IDP",
      "providerId": "basic-flow",
      "topLevel": true,
      "builtIn": true,
      "authenticationExecutions": [
        {
          "authenticator": "docker-http-basic-authenticator",
          "requirement": "REQUIRED",
          "priority": 10,
          "userSetupAllowed": false,
          "autheticatorFlow": false
        }
      ]
    },
    {
      "id": "34e93717-7453-4ac9-91ff-97d2c1ba0f80",
      "alias": "first broker login",
      "description": "Actions taken after first broker login with identity provider account, which is not yet linked to any Keycloak account",
      "providerId": "basic-flow",
      "topLevel": true,
      "builtIn": true,
      "authenticationExecutions": [
        {
          "authenticatorConfig": "review profile config",
          "authenticator": "idp-review-profile",
          "requirement": "REQUIRED",
          "priority": 10,
          "userSetupAllowed": false,
          "autheticatorFlow": false
        },
        {
          "authenticatorConfig": "create unique user config",
          "authenticator": "idp-create-user-if-unique",
          "requirement": "ALTERNATIVE",
          "priority": 20,
          "userSetupAllowed": false,
          "autheticatorFlow": false
        },
        {
          "requirement": "ALTERNATIVE",
          "priority": 30,
          "flowAlias": "Handle Existing Account",
          "userSetupAllowed": false,
          "autheticatorFlow": true
        }
      ]
    },
    {
      "id": "897f8a99-3152-42d9-b7aa-e6912250de7e",
      "alias": "forms",
      "description": "Username, password, otp and other auth forms.",
      "providerId": "basic-flow",
      "topLevel": false,
      "builtIn": true,
      "authenticationExecutions": [
        {
          "authenticator": "auth-username-password-form",
          "requirement": "REQUIRED",
          "priority": 10,
          "userSetupAllowed": false,
          "autheticatorFlow": false
        },
        {
          "authenticator": "auth-otp-form",
          "requirement": "OPTIONAL",
          "priority": 20,
          "userSetupAllowed": false,
          "autheticatorFlow": false
        }
      ]
    },
    {
      "id": "8dbb55fd-5dbf-4780-8fc6-f305c3673e1a",
      "alias": "registration",
      "description": "registration flow",
      "providerId": "basic-flow",
      "topLevel": true,
      "builtIn": true,
      "authenticationExecutions": [
        {
          "authenticator": "registration-page-form",
          "requirement": "REQUIRED",
          "priority": 10,
          "flowAlias": "registration form",
          "userSetupAllowed": false,
          "autheticatorFlow": true
        }
      ]
    },
    {
      "id": "646cf061-b8a5-4f5a-b7f6-613ccc178257",
      "alias": "registration - hmda",
      "description": "registration flow",
      "providerId": "basic-flow",
      "topLevel": true,
      "builtIn": false,
      "authenticationExecutions": [
        {
          "authenticator": "registration-page-form",
          "requirement": "REQUIRED",
          "priority": 10,
          "flowAlias": "registration - hmda registration form",
          "userSetupAllowed": false,
          "autheticatorFlow": true
        }
      ]
    },
    {
      "id": "a83fcec6-8635-40cf-be8e-030fce2648c1",
      "alias": "registration - hmda registration form",
      "description": "registration form",
      "providerId": "form-flow",
      "topLevel": false,
      "builtIn": false,
      "authenticationExecutions": [
        {
          "authenticator": "registration-user-creation",
          "requirement": "REQUIRED",
          "priority": 20,
          "userSetupAllowed": false,
          "autheticatorFlow": false
        },
        {
          "authenticator": "registration-profile-action",
          "requirement": "REQUIRED",
          "priority": 40,
          "userSetupAllowed": false,
          "autheticatorFlow": false
        },
        {
          "authenticator": "registration-password-action",
          "requirement": "REQUIRED",
          "priority": 50,
          "userSetupAllowed": false,
          "autheticatorFlow": false
        },
        {
          "authenticator": "registration-institution-action",
          "requirement": "REQUIRED",
          "priority": 61,
          "userSetupAllowed": false,
          "autheticatorFlow": false
        }
      ]
    },
    {
      "id": "799c827d-a4ea-4d3f-9e8f-5854aea2cc3a",
      "alias": "registration form",
      "description": "registration form",
      "providerId": "form-flow",
      "topLevel": false,
      "builtIn": true,
      "authenticationExecutions": [
        {
          "authenticator": "registration-user-creation",
          "requirement": "REQUIRED",
          "priority": 20,
          "userSetupAllowed": false,
          "autheticatorFlow": false
        },
        {
          "authenticator": "registration-profile-action",
          "requirement": "REQUIRED",
          "priority": 40,
          "userSetupAllowed": false,
          "autheticatorFlow": false
        },
        {
          "authenticator": "registration-password-action",
          "requirement": "REQUIRED",
          "priority": 50,
          "userSetupAllowed": false,
          "autheticatorFlow": false
        },
        {
          "authenticator": "registration-recaptcha-action",
          "requirement": "DISABLED",
          "priority": 60,
          "userSetupAllowed": false,
          "autheticatorFlow": false
        }
      ]
    },
    {
      "id": "208f5ee5-8abb-438e-b704-b7105cee5646",
      "alias": "reset credentials",
      "description": "Reset credentials for a user if they forgot their password or something",
      "providerId": "basic-flow",
      "topLevel": true,
      "builtIn": true,
      "authenticationExecutions": [
        {
          "authenticator": "reset-credentials-choose-user",
          "requirement": "REQUIRED",
          "priority": 10,
          "userSetupAllowed": false,
          "autheticatorFlow": false
        },
        {
          "authenticator": "reset-credential-email",
          "requirement": "REQUIRED",
          "priority": 20,
          "userSetupAllowed": false,
          "autheticatorFlow": false
        },
        {
          "authenticator": "reset-password",
          "requirement": "REQUIRED",
          "priority": 30,
          "userSetupAllowed": false,
          "autheticatorFlow": false
        },
        {
          "authenticator": "reset-otp",
          "requirement": "OPTIONAL",
          "priority": 40,
          "userSetupAllowed": false,
          "autheticatorFlow": false
        }
      ]
    },
    {
      "id": "3ce08c23-9ddd-40b7-9283-0cf617c018c2",
      "alias": "saml ecp",
      "description": "SAML ECP Profile Authentication Flow",
      "providerId": "basic-flow",
      "topLevel": true,
      "builtIn": true,
      "authenticationExecutions": [
        {
          "authenticator": "http-basic-authenticator",
          "requirement": "REQUIRED",
          "priority": 10,
          "userSetupAllowed": false,
          "autheticatorFlow": false
        }
      ]
    }
  ],
  "authenticatorConfig": [
    {
      "id": "86635688-10bc-4a0c-b272-43f4adab063b",
      "alias": "create unique user config",
      "config": {
        "require.password.update.after.registration": "false"
      }
    },
    {
      "id": "f7560951-d5d5-4604-a962-16ce6ab73595",
      "alias": "review profile config",
      "config": {
        "update.profile.on.first.login": "missing"
      }
    }
  ],
  "requiredActions": [
    {
      "alias": "CONFIGURE_TOTP",
      "name": "Configure OTP",
      "providerId": "CONFIGURE_TOTP",
      "enabled": true,
      "defaultAction": false,
      "config": {}
    },
    {
      "alias": "UPDATE_PASSWORD",
      "name": "Update Password",
      "providerId": "UPDATE_PASSWORD",
      "enabled": true,
      "defaultAction": false,
      "config": {}
    },
    {
      "alias": "UPDATE_PROFILE",
      "name": "Update Profile",
      "providerId": "UPDATE_PROFILE",
      "enabled": true,
      "defaultAction": false,
      "config": {}
    },
    {
      "alias": "VERIFY_EMAIL",
      "name": "Verify Email",
      "providerId": "VERIFY_EMAIL",
      "enabled": true,
      "defaultAction": false,
      "config": {}
    },
    {
      "alias": "terms_and_conditions",
      "name": "Terms and Conditions",
      "providerId": "terms_and_conditions",
      "enabled": false,
      "defaultAction": false,
      "config": {}
    }
  ],
  "browserFlow": "browser",
  "registrationFlow": "registration - hmda",
  "directGrantFlow": "direct grant",
  "resetCredentialsFlow": "reset credentials",
  "clientAuthenticationFlow": "clients",
  "dockerAuthenticationFlow": "docker auth",
  "attributes": {
    "_browser_header.xXSSProtection": "1; mode=block",
    "_browser_header.xFrameOptions": "SAMEORIGIN",
    "quickLoginCheckMilliSeconds": "1000",
    "permanentLockout": "true",
    "_browser_header.xRobotsTag": "none",
    "maxFailureWaitSeconds": "900",
    "minimumQuickLoginWaitSeconds": "60",
    "failureFactor": "30",
    "actionTokenGeneratedByUserLifespan": "3600",
    "maxDeltaTimeSeconds": "43200",
    "_browser_header.xContentTypeOptions": "nosniff",
    "actionTokenGeneratedByAdminLifespan": "43200",
    "bruteForceProtected": "true",
    "_browser_header.contentSecurityPolicy": "frame-src 'self'; frame-ancestors 'self'; object-src 'none';",
    "waitIncrementSeconds": "60"
  },
  "keycloakVersion": "4.5.0.Final"
}
